sorceress/__init__.py
sorceress/sorceress.py
sorceress-1.8.8.dist-info/METADATA
sorceress-1.8.8.dist-info/WHEEL
sorceress-1.8.8.dist-info/RECORD
