Metadata-Version: 2.1
Name: sorceress
Version: 1.8.8
Summary: Python package for creating optical illusions
Home-page: https://github.com/altunenes/sorceress
License: MIT
Keywords: optical-illusions,illusions,python,perception,image processing,psychology,vision,neuroscience,altunenes
Author: altunenes
Author-email: enesaltun2@gmail.com
Requires-Python: >=3.6,<4.0
Classifier: License :: OSI Approved :: MIT License
Classifier: Operating System :: OS Independent
Classifier: Programming Language :: Python :: 3
Classifier: Programming Language :: Python :: 3.6
Classifier: Programming Language :: Python :: 3.7
Classifier: Programming Language :: Python :: 3.8
Classifier: Programming Language :: Python :: 3.9
Classifier: Programming Language :: Python :: 3.10
Classifier: Programming Language :: Python :: 3.11
Classifier: Programming Language :: Python :: 3
Classifier: Programming Language :: Python :: 3.6
Classifier: Programming Language :: Python :: 3.7
Classifier: Programming Language :: Python :: 3.8
Classifier: Programming Language :: Python :: 3.9
